chroma_store/__about__.py
chroma_store/__init__.py
chroma_store/document_store.py
chroma_store/retriever.py
chroma_store-0.0.1.dist-info/METADATA
chroma_store-0.0.1.dist-info/WHEEL
chroma_store-0.0.1.dist-info/licenses/LICENSE
chroma_store-0.0.1.dist-info/RECORD
