Metadata-Version: 2.1
Name: chroma-store
Version: 0.0.1
Project-URL: Documentation, https://github.com/unknown/chroma-store#readme
Project-URL: Issues, https://github.com/unknown/chroma-store/issues
Project-URL: Source, https://github.com/unknown/chroma-store
Author-email: John Doe <jd@example.com>
License-Expression: Apache-2.0
License-File: LICENSE
Classifier: Development Status :: 4 - Beta
Classifier: Programming Language :: Python
Classifier: Programming Language :: Python :: 3.7
Classifier: Programming Language :: Python :: 3.8
Classifier: Programming Language :: Python :: 3.9
Classifier: Programming Language :: Python :: 3.10
Classifier: Programming Language :: Python :: 3.11
Classifier: Programming Language :: Python :: Implementation :: CPython
Classifier: Programming Language :: Python :: Implementation :: PyPy
Requires-Python: >=3.7
Requires-Dist: chromadb
Requires-Dist: farm-haystack
